.gitignore
AUTHORS
CHANGES
CONTRIBUTORS
LICENSE
MANIFEST.in
Makefile
README.rst
TODO
setup.py
examples/compression.erl
examples/compression.py
examples/generator.erl
examples/generator.py
examples/handler.erl
examples/handler.py
examples/hello.erl
examples/hello.py
src/erlport/__init__.py
src/erlport/erlproto.py
src/erlport/erlterms.py
src/erlport.egg-info/PKG-INFO
src/erlport.egg-info/SOURCES.txt
src/erlport.egg-info/dependency_links.txt
src/erlport.egg-info/top_level.txt
src/erlport.egg-info/zip-safe
src/erlport/tests/__init__.py
src/erlport/tests/erlproto.txt
src/erlport/tests/erlterms.txt