Metadata-Version: 1.0
Name: erlport
Version: 0.6
Summary: Erlang port protocol
Home-page: http://github.com/hdima/erlport
Author: Dmitry Vasiliev
Author-email: dima@hlabs.spb.ru
License: BSD
Keywords: Python Erlang
Platform: any
Classifier: Development Status :: 4 - Beta
Classifier: Environment :: Console
Classifier: Intended Audience :: Developers
Classifier: License :: OSI Approved :: BSD License
Classifier: Operating System :: OS Independent
Classifier: Programming Language :: Python
Classifier: Topic :: Software Development :: Libraries
